.DS_Store
datalens/__init__.py
datalens/app.py
datalens/visualise.py
datalens-0.1.dist-info/METADATA
datalens-0.1.dist-info/WHEEL
datalens-0.1.dist-info/top_level.txt
datalens-0.1.dist-info/RECORD
