Metadata-Version: 2.1
Name: datalens
Version: 0.1
Summary: A small example package
Home-page: https://github.com/namanjn98/datalens
Author: Naman Jain
Author-email: naman.j@alumni.iitgn.ac.in
License: UNKNOWN
Platform: UNKNOWN
Classifier: Programming Language :: Python :: 3
Classifier: License :: OSI Approved :: MIT License
Classifier: Operating System :: OS Independent
Requires-Python: >=3.6
